{
  "name": "currentSession",
  "files": [
    {
      "name": "currentSession.ts",
      "content": "\n import { auth } from \"@/auth\";\nexport async function currentUserServer() {\n  try {\n    const session = await auth();\n    if (session) {\n      return session.user;\n    }\n    return null;\n  } catch (error) {\n    console.log(error);\n  }\n} \n\nexport const useCurrentUser=\n () => {\n        const session = useSession();\n              return session.data?.user;\n  };\n "
    }
  ],
  "type": "lib:utils"
}
